Workbook

Sheet 前提
A1: 前提
A3: ■ この資料の性格
B4: 金額はすべて未入力。埋めるまで損益はゼロのまま出ます。こちらで単価や人件費を推測して置くことはしていません。
A6: ■ 検証済みの数字（確定）
A7: 対象リスト 1,308件 | B7: 民間(営利法人)×都内1事業所×独立系×全国1事業所。元データと照合済み
A8: 東京都 全2,893件 | B8: うち1法人1事業所が1,910件（法人番号で名寄せ）
A9: 全国 36,212件 | B9: 全行が サービスの種類=居宅介護支援
A10: 電話番号 | B10: 全件が元データと一致。欠損ゼロ
A12: ■ 仮置きの数字（実測で置き換える）
A13: ファネル4率 | B13: 無効3% / アポ3% / 商談80% / 受注20%。評価基準シートの目標値であり、業界の実績値ではない
A14: 1人1日50件 | B14: 架電の所要時間を測っていないため仮。実測が出たら入力シートを更新する
A16: ■ このモデルが示す構造的な論点
A17: リストは有限 | B17: 流入経路がゼロなので、売上の上限はリスト件数で決まる。現行1,308件は3人×50件/日で約9営業日で尽きる
A18: 売上が人数に比例する | B18: 架電だけだと、売上を伸ばす手段が人を増やすことしかない。利益率が構造的に上がらない
A19: 枯渇後もコストは出る | B19: 架電が止まっても人件費は消えない。既定では枯渇後も固定費を計上する。月次P&Lで赤字が続くのはその表現
A20: 在庫を広げるか、経路を作るか | B20: 全国に広げれば約12ヶ月分。その間にSNS・Webの流入を立ち上げるかどうかが分岐点
A22: ■ 使い方
A23: 1 | B23: 入力シートの黄色いセルを埋める
A24: 2 | B24: 損益分岐シートの上の表で、必要な単価が今の価格で届くか見る
A25: 3 | B25: 月次P&Lで、何ヶ月目に累計黒字になるか確認する
A26: 4 | B26: 在庫シナリオで、どこまでリストを広げるか決める

Sheet 入力
A1: 入力
A2: 黄色のセルを埋めてください。緑は検証済みの確定値です。
A3: 数量
A4: 対象リスト件数 | B4: 1308 | C4: 件 | D4: 確定。tokyo_minkan_1jigyosho.csv の行数
A5: 稼働人数 | B5: 3 | C5: 人 | D5: しょうちゃん・さくや・廣澤
A6: 1人1日あたり架電数 | B6: 50 | C6: 件 | D6: 実測が出たら置き換える
A7: 月間稼働日数 | B7: 20 | C7: 日
A8: 無効リード率 | B8: 0.03 | C8: 率 | D8: 番号違い・対象外。評価基準の目標値（仮）
A9: アポ率(有効架電比) | B9: 0.03 | C9: 率 | D9: 評価基準の目標値（仮）
A10: 商談実施率 | B10: 0.8 | C10: 率 | D10: 評価基準の目標値（仮）
A11: 受注率(商談比) | B11: 0.2 | C11: 率 | D11: 評価基準の目標値（仮）
A13: 金額（未入力）
A15: 初回単価 | C15: 円 | D15: 1件受注したときの初回売上
A16: 月額継続課金 | C16: 円/月 | D16: 無ければ0
A17: 平均継続月数 | C17: ヶ月 | D17: 月額課金がある場合。無ければ0
A18: 変動費率 | C18: 率 | D18: 原価・外注費の売上に対する比率
A19: 人件費(1人あたり月) | C19: 円 | D19: 3人分は自動で掛ける
A20: 通信・ツール費(月) | C20: 円 | D20: 電話・CRM等
A21: その他固定費(月) | C21: 円 | D21: 家賃・雑費など
A22: リスト枯渇後の固定費 | B22: 計上する | C22: 選択 | D22: 人員を維持するなら「計上する」。架電が止まっても人件費は消えない
A23: 自動計算
A24: 月間架電キャパ | B24: =入力!$B$5*入力!$B$6*入力!$B$7 | C24: 本/月 | D24: 3人が1ヶ月にかけられる本数
A25: 架電→受注の転換率 | B25: =(1-入力!$B$8)*入力!$B$9*入力!$B$10*入力!$B$11 | C25: 率 | D25: 架電1本が受注になる確率
A26: 1受注あたり必要架電数 | B26: =IFERROR(1/B24,"") | C26: 本
A27: 月間固定費計 | B27: =入力!$B$19*入力!$B$5+入力!$B$20+入力!$B$21 | C27: 円/月 | D27: 金額を入れると出ます

Sheet 月次P&L
A1: 月次P&L
A2: リストが尽きると架電数が自動で頭打ちになります。枯渇後も人員を維持する前提なら固定費は計上され続けます（入力シートで切り替え）。
A3: 月 | B3: 期首残リスト | C3: 架電数 | D3: 有効架電 | E3: アポ | F3: 商談 | G3: 受注 | H3: 期末残リスト | I3: 新規売上 | J3: 継続売上 | K3: 売上計 | L3: 変動費 | M3: 粗利 | N3: 固定費 | O3: 営業利益 | P3: 累計営業利益
A4: 1 | B4: =IF(A4=1,入力!$B$4,H3) | C4: =MIN(入力!$B$24,B4) | D4: =C4*(1-入力!$B$8) | E4: =D4*入力!$B$9 | F4: =E4*入力!$B$10 | G4: =F4*入力!$B$11 | H4: =B4-C4 | I4: =G4*入力!$B$15 | J4: =SUMIFS($G$4:$G$15,$A$4:$A$15,">="&A4-入力!$B$17+1,$A$4:$A$15,"<="&A4)*入力!$B$16 | K4: =I4+J4 | L4: =K4*入力!$B$18 | M4: =K4-L4 | N4: =IF(OR(入力!$B$22="計上する",C4>0),入力!$B$27,0) | O4: =M4-N4 | P4: =IF(A4=1,O4,P3+O4)
A5: 2 | B5: =IF(A5=1,入力!$B$4,H4) | C5: =MIN(入力!$B$24,B5) | D5: =C5*(1-入力!$B$8) | E5: =D5*入力!$B$9 | F5: =E5*入力!$B$10 | G5: =F5*入力!$B$11 | H5: =B5-C5 | I5: =G5*入力!$B$15 | J5: =SUMIFS($G$4:$G$15,$A$4:$A$15,">="&A5-入力!$B$17+1,$A$4:$A$15,"<="&A5)*入力!$B$16 | K5: =I5+J5 | L5: =K5*入力!$B$18 | M5: =K5-L5 | N5: =IF(OR(入力!$B$22="計上する",C5>0),入力!$B$27,0) | O5: =M5-N5 | P5: =IF(A5=1,O5,P4+O5)
A6: 3 | B6: =IF(A6=1,入力!$B$4,H5) | C6: =MIN(入力!$B$24,B6) | D6: =C6*(1-入力!$B$8) | E6: =D6*入力!$B$9 | F6: =E6*入力!$B$10 | G6: =F6*入力!$B$11 | H6: =B6-C6 | I6: =G6*入力!$B$15 | J6: =SUMIFS($G$4:$G$15,$A$4:$A$15,">="&A6-入力!$B$17+1,$A$4:$A$15,"<="&A6)*入力!$B$16 | K6: =I6+J6 | L6: =K6*入力!$B$18 | M6: =K6-L6 | N6: =IF(OR(入力!$B$22="計上する",C6>0),入力!$B$27,0) | O6: =M6-N6 | P6: =IF(A6=1,O6,P5+O6)
A7: 4 | B7: =IF(A7=1,入力!$B$4,H6) | C7: =MIN(入力!$B$24,B7) | D7: =C7*(1-入力!$B$8) | E7: =D7*入力!$B$9 | F7: =E7*入力!$B$10 | G7: =F7*入力!$B$11 | H7: =B7-C7 | I7: =G7*入力!$B$15 | J7: =SUMIFS($G$4:$G$15,$A$4:$A$15,">="&A7-入力!$B$17+1,$A$4:$A$15,"<="&A7)*入力!$B$16 | K7: =I7+J7 | L7: =K7*入力!$B$18 | M7: =K7-L7 | N7: =IF(OR(入力!$B$22="計上する",C7>0),入力!$B$27,0) | O7: =M7-N7 | P7: =IF(A7=1,O7,P6+O7)
A8: 5 | B8: =IF(A8=1,入力!$B$4,H7) | C8: =MIN(入力!$B$24,B8) | D8: =C8*(1-入力!$B$8) | E8: =D8*入力!$B$9 | F8: =E8*入力!$B$10 | G8: =F8*入力!$B$11 | H8: =B8-C8 | I8: =G8*入力!$B$15 | J8: =SUMIFS($G$4:$G$15,$A$4:$A$15,">="&A8-入力!$B$17+1,$A$4:$A$15,"<="&A8)*入力!$B$16 | K8: =I8+J8 | L8: =K8*入力!$B$18 | M8: =K8-L8 | N8: =IF(OR(入力!$B$22="計上する",C8>0),入力!$B$27,0) | O8: =M8-N8 | P8: =IF(A8=1,O8,P7+O8)
A9: 6 | B9: =IF(A9=1,入力!$B$4,H8) | C9: =MIN(入力!$B$24,B9) | D9: =C9*(1-入力!$B$8) | E9: =D9*入力!$B$9 | F9: =E9*入力!$B$10 | G9: =F9*入力!$B$11 | H9: =B9-C9 | I9: =G9*入力!$B$15 | J9: =SUMIFS($G$4:$G$15,$A$4:$A$15,">="&A9-入力!$B$17+1,$A$4:$A$15,"<="&A9)*入力!$B$16 | K9: =I9+J9 | L9: =K9*入力!$B$18 | M9: =K9-L9 | N9: =IF(OR(入力!$B$22="計上する",C9>0),入力!$B$27,0) | O9: =M9-N9 | P9: =IF(A9=1,O9,P8+O9)
A10: 7 | B10: =IF(A10=1,入力!$B$4,H9) | C10: =MIN(入力!$B$24,B10) | D10: =C10*(1-入力!$B$8) | E10: =D10*入力!$B$9 | F10: =E10*入力!$B$10 | G10: =F10*入力!$B$11 | H10: =B10-C10 | I10: =G10*入力!$B$15 | J10: =SUMIFS($G$4:$G$15,$A$4:$A$15,">="&A10-入力!$B$17+1,$A$4:$A$15,"<="&A10)*入力!$B$16 | K10: =I10+J10 | L10: =K10*入力!$B$18 | M10: =K10-L10 | N10: =IF(OR(入力!$B$22="計上する",C10>0),入力!$B$27,0) | O10: =M10-N10 | P10: =IF(A10=1,O10,P9+O10)
A11: 8 | B11: =IF(A11=1,入力!$B$4,H10) | C11: =MIN(入力!$B$24,B11) | D11: =C11*(1-入力!$B$8) | E11: =D11*入力!$B$9 | F11: =E11*入力!$B$10 | G11: =F11*入力!$B$11 | H11: =B11-C11 | I11: =G11*入力!$B$15 | J11: =SUMIFS($G$4:$G$15,$A$4:$A$15,">="&A11-入力!$B$17+1,$A$4:$A$15,"<="&A11)*入力!$B$16 | K11: =I11+J11 | L11: =K11*入力!$B$18 | M11: =K11-L11 | N11: =IF(OR(入力!$B$22="計上する",C11>0),入力!$B$27,0) | O11: =M11-N11 | P11: =IF(A11=1,O11,P10+O11)
A12: 9 | B12: =IF(A12=1,入力!$B$4,H11) | C12: =MIN(入力!$B$24,B12) | D12: =C12*(1-入力!$B$8) | E12: =D12*入力!$B$9 | F12: =E12*入力!$B$10 | G12: =F12*入力!$B$11 | H12: =B12-C12 | I12: =G12*入力!$B$15 | J12: =SUMIFS($G$4:$G$15,$A$4:$A$15,">="&A12-入力!$B$17+1,$A$4:$A$15,"<="&A12)*入力!$B$16 | K12: =I12+J12 | L12: =K12*入力!$B$18 | M12: =K12-L12 | N12: =IF(OR(入力!$B$22="計上する",C12>0),入力!$B$27,0) | O12: =M12-N12 | P12: =IF(A12=1,O12,P11+O12)
A13: 10 | B13: =IF(A13=1,入力!$B$4,H12) | C13: =MIN(入力!$B$24,B13) | D13: =C13*(1-入力!$B$8) | E13: =D13*入力!$B$9 | F13: =E13*入力!$B$10 | G13: =F13*入力!$B$11 | H13: =B13-C13 | I13: =G13*入力!$B$15 | J13: =SUMIFS($G$4:$G$15,$A$4:$A$15,">="&A13-入力!$B$17+1,$A$4:$A$15,"<="&A13)*入力!$B$16 | K13: =I13+J13 | L13: =K13*入力!$B$18 | M13: =K13-L13 | N13: =IF(OR(入力!$B$22="計上する",C13>0),入力!$B$27,0) | O13: =M13-N13 | P13: =IF(A13=1,O13,P12+O13)
A14: 11 | B14: =IF(A14=1,入力!$B$4,H13) | C14: =MIN(入力!$B$24,B14) | D14: =C14*(1-入力!$B$8) | E14: =D14*入力!$B$9 | F14: =E14*入力!$B$10 | G14: =F14*入力!$B$11 | H14: =B14-C14 | I14: =G14*入力!$B$15 | J14: =SUMIFS($G$4:$G$15,$A$4:$A$15,">="&A14-入力!$B$17+1,$A$4:$A$15,"<="&A14)*入力!$B$16 | K14: =I14+J14 | L14: =K14*入力!$B$18 | M14: =K14-L14 | N14: =IF(OR(入力!$B$22="計上する",C14>0),入力!$B$27,0) | O14: =M14-N14 | P14: =IF(A14=1,O14,P13+O14)
A15: 12 | B15: =IF(A15=1,入力!$B$4,H14) | C15: =MIN(入力!$B$24,B15) | D15: =C15*(1-入力!$B$8) | E15: =D15*入力!$B$9 | F15: =E15*入力!$B$10 | G15: =F15*入力!$B$11 | H15: =B15-C15 | I15: =G15*入力!$B$15 | J15: =SUMIFS($G$4:$G$15,$A$4:$A$15,">="&A15-入力!$B$17+1,$A$4:$A$15,"<="&A15)*入力!$B$16 | K15: =I15+J15 | L15: =K15*入力!$B$18 | M15: =K15-L15 | N15: =IF(OR(入力!$B$22="計上する",C15>0),入力!$B$27,0) | O15: =M15-N15 | P15: =IF(A15=1,O15,P14+O15)

Sheet 損益分岐
A1: 損益分岐
A2: 上の表は単価を入れなくても読めます。月次固定費と月あたり受注件数から、必要な単価が出ます。
A4: 必要単価の逆算（粗利率は入力シートの変動費率から算出）
A5: 月次固定費 \ 月間受注件数 | B5: 1件 | C5: 2件 | D5: 4件 | E5: 6件 | F5: 10件 | G5: 15件
A6: 300000 | B6: =IFERROR($A6/(1*(1-入力!$B$18)),"変動費率を入力") | C6: =IFERROR($A6/(2*(1-入力!$B$18)),"変動費率を入力") | D6: =IFERROR($A6/(4*(1-入力!$B$18)),"変動費率を入力") | E6: =IFERROR($A6/(6*(1-入力!$B$18)),"変動費率を入力") | F6: =IFERROR($A6/(10*(1-入力!$B$18)),"変動費率を入力") | G6: =IFERROR($A6/(15*(1-入力!$B$18)),"変動費率を入力")
A7: 600000 | B7: =IFERROR($A7/(1*(1-入力!$B$18)),"変動費率を入力") | C7: =IFERROR($A7/(2*(1-入力!$B$18)),"変動費率を入力") | D7: =IFERROR($A7/(4*(1-入力!$B$18)),"変動費率を入力") | E7: =IFERROR($A7/(6*(1-入力!$B$18)),"変動費率を入力") | F7: =IFERROR($A7/(10*(1-入力!$B$18)),"変動費率を入力") | G7: =IFERROR($A7/(15*(1-入力!$B$18)),"変動費率を入力")
A8: 1000000 | B8: =IFERROR($A8/(1*(1-入力!$B$18)),"変動費率を入力") | C8: =IFERROR($A8/(2*(1-入力!$B$18)),"変動費率を入力") | D8: =IFERROR($A8/(4*(1-入力!$B$18)),"変動費率を入力") | E8: =IFERROR($A8/(6*(1-入力!$B$18)),"変動費率を入力") | F8: =IFERROR($A8/(10*(1-入力!$B$18)),"変動費率を入力") | G8: =IFERROR($A8/(15*(1-入力!$B$18)),"変動費率を入力")
A9: 1500000 | B9: =IFERROR($A9/(1*(1-入力!$B$18)),"変動費率を入力") | C9: =IFERROR($A9/(2*(1-入力!$B$18)),"変動費率を入力") | D9: =IFERROR($A9/(4*(1-入力!$B$18)),"変動費率を入力") | E9: =IFERROR($A9/(6*(1-入力!$B$18)),"変動費率を入力") | F9: =IFERROR($A9/(10*(1-入力!$B$18)),"変動費率を入力") | G9: =IFERROR($A9/(15*(1-入力!$B$18)),"変動費率を入力")
A10: 2000000 | B10: =IFERROR($A10/(1*(1-入力!$B$18)),"変動費率を入力") | C10: =IFERROR($A10/(2*(1-入力!$B$18)),"変動費率を入力") | D10: =IFERROR($A10/(4*(1-入力!$B$18)),"変動費率を入力") | E10: =IFERROR($A10/(6*(1-入力!$B$18)),"変動費率を入力") | F10: =IFERROR($A10/(10*(1-入力!$B$18)),"変動費率を入力") | G10: =IFERROR($A10/(15*(1-入力!$B$18)),"変動費率を入力")
A13: 実際の入力値での損益分岐
A14: 1件あたり粗利 | B14: =入力!$B$15*(1-入力!$B$18)+入力!$B$16*入力!$B$17*(1-入力!$B$18) | C14: 円
A15: 損益分岐に必要な月間受注件数 | B15: =IFERROR(入力!$B$27/B14,"") | C15: 件
A16: そのために必要な月間架電数 | B16: =IFERROR(B15/入力!$B$25,"") | C16: 本
A17: 現在のキャパでの充足 | B17: =IFERROR(入力!$B$24/B16,"") | C17: 倍 | D17: 1.0倍未満なら、今の人数では黒字化に届かない
A18: リストが尽きるまでの月数 | B18: =IFERROR(入力!$B$4/入力!$B$24,"") | C18: ヶ月

Sheet 在庫シナリオ
A1: 在庫シナリオ
A2: 流入経路がゼロのため、売上はリスト在庫に上限が決まります。どこまで広げるかが最大の論点です。
A4: 広げ方 | B4: 件数 | C4: 枯渇まで(月) | D4: 累計受注(目標値) | E4: 累計売上 | F4: 内容
A5: 現行の最終リスト | B5: 1308 | C5: =IFERROR(B5/入力!$B$24,"") | D5: =B5*入力!$B$25 | E5: =D5*(入力!$B$15+入力!$B$16*入力!$B$17) | F5: 民間×都内1事業所×独立系×全国1事業所
A6: ＋除外を戻す | B6: 1910 | C6: =IFERROR(B6/入力!$B$24,"") | D6: =B6*入力!$B$25 | E6: =D6*(入力!$B$15+入力!$B$16*入力!$B$17) | F6: 併設・他県拠点・非営利を含める
A7: ＋東京の多数事業所 | B7: 2893 | C7: =IFERROR(B7/入力!$B$24,"") | D7: =B7*入力!$B$25 | E7: =D7*(入力!$B$15+入力!$B$16*入力!$B$17) | F7: スイング側と合流。東京を全部使う
A8: ＋全国に広げる | B8: 36212 | C8: =IFERROR(B8/入力!$B$24,"") | D8: =B8*入力!$B$25 | E8: =D8*(入力!$B$15+入力!$B$16*入力!$B$17) | F8: 同じ条件で全国。データは取得済み
